pycircos/__init__.py
pycircos/pycircos.py
python_circos-0.2.0.dist-info/LICENSE
python_circos-0.2.0.dist-info/METADATA
python_circos-0.2.0.dist-info/WHEEL
python_circos-0.2.0.dist-info/top_level.txt
python_circos-0.2.0.dist-info/RECORD
