Metadata-Version: 2.1
Name: python-circos
Version: 0.2.0
Summary: circosplot for matplotlib
Home-page: https://github.com/ponnhide/pyCircos
Author: Hideto Mori
Author-email: hidto7592@gmail.com
Maintainer: Hideto Mori
Maintainer-email: hidto7592@gmail.com
License: GNU General Public License v3.0
Download-URL: https://github.com/ponnhide/pyCircos
Platform: UNKNOWN
Classifier: Intended Audience :: Science/Research
Classifier: Programming Language :: Python :: 3.7
Classifier: Programming Language :: Python :: 3.8
Classifier: Programming Language :: Python :: 3.9
Classifier: License :: OSI Approved :: GNU General Public License v3 (GPLv3)
Requires-Python: >=3.7
License-File: LICENSE
Requires-Dist: matplotlib (>=3.4)
Requires-Dist: biopython (>=1.78)
